flytekit/__init__.py
flytekit/loggers.py
flytekit/bin/__init__.py
flytekit/bin/entrypoint.py
flytekit/clients/__init__.py
flytekit/clients/friendly.py
flytekit/clients/helpers.py
flytekit/clients/raw.py
flytekit/clis/__init__.py
flytekit/clis/helpers.py
flytekit/clis/auth/__init__.py
flytekit/clis/auth/auth.py
flytekit/clis/auth/credentials.py
flytekit/clis/flyte_cli/__init__.py
flytekit/clis/flyte_cli/main.py
flytekit/clis/sdk_in_container/__init__.py
flytekit/clis/sdk_in_container/constants.py
flytekit/clis/sdk_in_container/init.py
flytekit/clis/sdk_in_container/local_cache.py
flytekit/clis/sdk_in_container/package.py
flytekit/clis/sdk_in_container/pyflyte.py
flytekit/clis/sdk_in_container/run.py
flytekit/clis/sdk_in_container/serialize.py
flytekit/configuration/__init__.py
flytekit/configuration/default_images.py
flytekit/configuration/feature_flags.py
flytekit/configuration/file.py
flytekit/configuration/internal.py
flytekit/core/__init__.py
flytekit/core/annotation.py
flytekit/core/base_task.py
flytekit/core/checkpointer.py
flytekit/core/class_based_resolver.py
flytekit/core/condition.py
flytekit/core/constants.py
flytekit/core/container_task.py
flytekit/core/context_manager.py
flytekit/core/data_persistence.py
flytekit/core/docstring.py
flytekit/core/dynamic_workflow_task.py
flytekit/core/hash.py
flytekit/core/interface.py
flytekit/core/launch_plan.py
flytekit/core/local_cache.py
flytekit/core/map_task.py
flytekit/core/mock_stats.py
flytekit/core/node.py
flytekit/core/node_creation.py
flytekit/core/notification.py
flytekit/core/promise.py
flytekit/core/python_auto_container.py
flytekit/core/python_customized_container_task.py
flytekit/core/python_function_task.py
flytekit/core/reference.py
flytekit/core/reference_entity.py
flytekit/core/resources.py
flytekit/core/schedule.py
flytekit/core/shim_task.py
flytekit/core/task.py
flytekit/core/testing.py
flytekit/core/tracked_abc.py
flytekit/core/tracker.py
flytekit/core/type_engine.py
flytekit/core/type_helpers.py
lytekit-0.15.30.dist-info/licenses/LICENSE
lytekit-0.15.30.dist-info/METADATA
lytekit-0.15.30.dist-info/WHEEL
lytekit-0.15.30.dist-info/entry_points.txt
lytekit-0.15.30.dist-info/top_level.txt
lytekit-0.15.30.dist-info/RECORD
