Metadata-Version: 2.4
Name: lytekit
Version: 0.15.30
Summary: Flyte SDK for Python
Home-page: https://github.com/flyteorg/flytekit
Maintainer: Flyte Contributors
Maintainer-email: contact@latch.bio
License: apache2
Classifier: Intended Audience :: Science/Research
Classifier: Intended Audience :: Developers
Classifier: License :: OSI Approved :: Apache Software License
Classifier: Programming Language :: Python :: 3.7
Classifier: Programming Language :: Python :: 3.8
Classifier: Programming Language :: Python :: 3.9
Classifier: Programming Language :: Python :: 3.10
Classifier: Topic :: Scientific/Engineering
Classifier: Topic :: Scientific/Engineering :: Artificial Intelligence
Classifier: Topic :: Software Development
Classifier: Topic :: Software Development :: Libraries
Classifier: Topic :: Software Development :: Libraries :: Python Modules
Requires-Python: >=3.7
License-File: LICENSE
Requires-Dist: lyteidl==0.2.1
Requires-Dist: wheel<1.0.0,>=0.30.0
Requires-Dist: click<9.0,>=6.6
Requires-Dist: croniter<4.0.0,>=0.3.20
Requires-Dist: deprecated<2.0,>=1.0
Requires-Dist: docker>=7.1.0
Requires-Dist: python-dateutil>=2.1
Requires-Dist: grpcio!=1.45.0,<2.0,>=1.43.0
Requires-Dist: grpcio-status!=1.45.0,>=1.43
Requires-Dist: protobuf<4,>=3.6.1
Requires-Dist: python-json-logger>=2.0.0
Requires-Dist: pytimeparse<2.0.0,>=1.1.8
Requires-Dist: pytz
Requires-Dist: keyring>=18.0.1
Requires-Dist: requests<3.0.0,>=2.18.4
Requires-Dist: responses>=0.10.7
Requires-Dist: sortedcontainers<3.0.0,>=1.5.9
Requires-Dist: statsd<4.0.0,>=3.0.0
Requires-Dist: urllib3<2.0.0,>=1.22
Requires-Dist: wrapt<2.0.0,>=1.0.0
Requires-Dist: retry==0.9.2
Requires-Dist: dataclasses-json<=0.5.6,>=0.5.2
Requires-Dist: jsonschema>=4.5.1
Requires-Dist: marshmallow-jsonschema>=0.12.0
Requires-Dist: marshmallow_enum
Requires-Dist: natsort>=7.0.1
Requires-Dist: docker-image-py>=0.1.10
Requires-Dist: singledispatchmethod; python_version < "3.8.0"
Requires-Dist: typing_extensions>=4.7.1
Requires-Dist: docstring-parser>=0.9.0
Requires-Dist: diskcache>=5.2.1
Requires-Dist: cloudpickle>=2.0.0
Requires-Dist: cookiecutter>=1.7.3
Requires-Dist: latch_persistence==0.1.5
Requires-Dist: memory_profiler==0.61.0
Dynamic: classifier
Dynamic: description
Dynamic: description-content-type
Dynamic: home-page
Dynamic: license
Dynamic: license-file
Dynamic: maintainer
Dynamic: maintainer-email
Dynamic: requires-dist
Dynamic: requires-python
Dynamic: summary
